future_map/__init__.py
future_map/future_map.py
future_map-0.1.2.dist-info/LICENSE
future_map-0.1.2.dist-info/WHEEL
future_map-0.1.2.dist-info/METADATA
future_map-0.1.2.dist-info/RECORD
