Metadata-Version: 2.1
Name: future-map
Version: 0.1.2
Summary: Simple package to enhance Python's concurrent.futures for memory efficiency
Home-page: https://github.com/hiroara/future-map
License: MIT
Keywords: concurrency,thread-pool,process-pool,future,executor
Author: Arai Hiroki
Author-email: hiroara62@gmail.com
Requires-Python: >=3.8,<4.0
Classifier: License :: OSI Approved :: MIT License
Classifier: Programming Language :: Python :: 3
Classifier: Programming Language :: Python :: 3.8
Classifier: Programming Language :: Python :: 3.9
Project-URL: Repository, https://github.com/hiroara/future-map.git
